{
  "categories": [
    { "id": "cat1", "slug": "home", "label": "Home", "emoji": "🏠", "description": "Home decor, organization, and living essentials" },
    { "id": "cat2", "slug": "beauty", "label": "Beauty", "emoji": "💄", "description": "Skincare, makeup, and personal care" },
    { "id": "cat3", "slug": "fitness", "label": "Fitness", "emoji": "💪", "description": "Workout gear, supplements, and wellness" },
    { "id": "cat4", "slug": "gadgets", "label": "Gadgets", "emoji": "📱", "description": "Tech, electronics, and smart devices" },
    { "id": "cat5", "slug": "fashion", "label": "Fashion", "emoji": "👗", "description": "Clothing, accessories, and footwear" },
    { "id": "cat6", "slug": "food", "label": "Food & Kitchen", "emoji": "🍳", "description": "Cooking tools, ingredients, and kitchen gadgets" }
  ],
  "products": []
}